telebaka_feed/__init__.py
telebaka_feed/admin.py
telebaka_feed/bot.py
telebaka_feed/models.py
telebaka_feed/preferences.py
telebaka_feed/tasks.py
telebaka_feed/migrations/0001_initial.py
telebaka_feed/migrations/0002_auto_20180701_1444.py
telebaka_feed/migrations/__init__.py
telebaka_feed-0.1.11.dist-info/METADATA
telebaka_feed-0.1.11.dist-info/RECORD
telebaka_feed-0.1.11.dist-info/WHEEL
telebaka_feed-0.1.11.dist-info/top_level.txt
